{"is_source_file": false, "format": "", "description": "", "external_files": [], "external_methods": [], "published": [], "classes": [], "methods": [], "calls": [], "search-terms": [], "state": 2, "file_id": 1, "knowledge_revision": 19, "git_revision": "f68ad98ff340437fde3e36cd355f51c3a47b39bb", "hash": "d001d53c059625c4bcf75bf5a7f3fcf0", "format-version": 4, "code-base-name": "nurse_portal_frontend", "filename": "nurse_portal_frontend/package.json", "revision_history": [{"19": "f68ad98ff340437fde3e36cd355f51c3a47b39bb"}]}